README.md
pyproject.toml
setup.py
src/serrelabmodels/__init__.py
src/serrelabmodels/gamanet.py
src/serrelabmodels/hgru.py
src/serrelabmodels/main.py
src/serrelabmodels.egg-info/PKG-INFO
src/serrelabmodels.egg-info/SOURCES.txt
src/serrelabmodels.egg-info/dependency_links.txt
src/serrelabmodels.egg-info/not-zip-safe
src/serrelabmodels.egg-info/top_level.txt
src/serrelabmodels/layers/__init__.py
src/serrelabmodels/layers/fgru_cell.py
src/serrelabmodels/layers/hgru_cell.py
src/serrelabmodels/models/__init__.py
src/serrelabmodels/models/vgg_16.py
src/serrelabmodels/models/vgg_hgru.py
src/serrelabmodels/ops/__init__.py
src/serrelabmodels/ops/model_tools.py
src/serrelabmodels/utils/__init__.py
src/serrelabmodels/utils/c_x.py
src/serrelabmodels/utils/pt_utils.py
src/serrelabmodels/utils/py_utils.py