Metadata-Version: 2.1
Name: serrelabmodels
Version: 0.0.4
Summary: Package to import in-house models from the Serre Lab at Brown University.
Home-page: https://github.com/serre-lab/serrelabmodels
Author: Akash Nagaraj
Author-email: akash_n@brown.edu
License: UNKNOWN
Project-URL: Documentation, https://github.com/serre-lab/serrelabmodels/docs
Platform: UNKNOWN
Classifier: Programming Language :: Python :: 3
Classifier: License :: OSI Approved :: MIT License
Classifier: Operating System :: OS Independent
Requires-Python: >=3.6
